{
    "team": [
        {
            "name": "Michael Benefiel",
            "designation": "Front End Developer",
            "photo": "mike.jpg",
            "facebook": "https: //www.facebook.com/",
            "twitter": "https://twitter.com/",
            "linkedin": "https://linkedin.com/",
            "github": "https://github.com/",
            "desc": "Coding ninja, skilled in the art and craft of guruing and slicing fruit",
            "mongo": "https://www.mongodb.com/",
            "express": "https://expressjs.com/",
            "react": "https://reactjs.org/",
            "node": "https://nodejs.org/en/",
            "javascript": "https://www.javascript.com/"
        },
        {
            "name": "Spencer Knoll",
            "designation": "Front End Developer",
            "photo": "spencer.jpg",
            "facebook": "https: //www.facebook.com/",
            "twitter": "https://twitter.com/",
            "linkedin": "https://linkedin.com/",
            "github": "https://github.com/",
            "desc": "Coding ninja, skilled in the art and craft of guruing and slicing fruit",
            "mongo": "https://www.mongodb.com/",
            "express": "https://expressjs.com/",
            "react": "https://reactjs.org/",
            "node": "https://nodejs.org/en/",
            "javascript": "https://www.javascript.com/"
        },
        {
            "name": "Dustin Watkins",
            "designation": "Back End Developer",
            "photo": "dustin.jpg",
            "facebook": "https: //www.facebook.com/",
            "twitter": "https://twitter.com/",
            "linkedin": "https://linkedin.com/",
            "github": "https://github.com/",
            "desc": "Coding ninja, skilled in the art and craft of guruing and slicing fruit",
            "mongo": "https://www.mongodb.com/",
            "express": "https://expressjs.com/",
            "react": "https://reactjs.org/",
            "node": "https://nodejs.org/en/",
            "javascript": "https://www.javascript.com/"
        },
        {
            "name": "Tim Lukens",
            "designation": "Back End Developer",
            "photo": "tim.jpg",
            "facebook": "https: //www.facebook.com/",
            "twitter": "https://twitter.com/",
            "linkedin": "https://linkedin.com/",
            "github": "https://github.com/",
            "desc": "Coding ninja, skilled in the art and craft of guruing and slicing fruit",
            "mongo": "https://www.mongodb.com/",
            "express": "https://expressjs.com/",
            "react": "https://reactjs.org/",
            "node": "https://nodejs.org/en/",
            "javascript": "https://www.javascript.com/"
        },
        {
            "name": "Pirate Dude",
            "designation": "Captain",
            "photo": "4.jpg",
            "facebook": "https: //www.facebook.com/",
            "twitter": "https://twitter.com/",
            "linkedin": "https://linkedin.com/",
            "github": "https://github.com/",
            "desc": "Coding ninja, skilled in the art and craft of guruing and slicing fruit",
            "mongo": "https://www.mongodb.com/",
            "express": "https://expressjs.com/",
            "react": "https://reactjs.org/",
            "node": "https://nodejs.org/en/",
            "javascript": "https://www.javascript.com/"
        },
        {
            "name": "Black Hat Ninja",
            "designation": "Backroom Dealer",
            "photo": "3.jpg",
            "facebook": "https: //www.facebook.com/",
            "twitter": "https://twitter.com/",
            "linkedin": "https://linkedin.com/",
            "github": "https://github.com/",
            "desc": "Coding ninja, skilled in the art and craft of guruing and slicing fruit",
            "mongo": "https://www.mongodb.com/",
            "express": "https://expressjs.com/",
            "react": "https://reactjs.org/",
            "node": "https://nodejs.org/en/",
            "javascript": "https://www.javascript.com/"
        }
    ]
}